FinanceDataReader/__init__.py
FinanceDataReader/_utils.py
FinanceDataReader/back_chart.py
FinanceDataReader/data.py
FinanceDataReader/chart/__init__.py
FinanceDataReader/chart/candle.py
FinanceDataReader/chart/plot.py
FinanceDataReader/ecos/__init__.py
FinanceDataReader/ecos/data.py
FinanceDataReader/ecos/snap.py
FinanceDataReader/fred/__init__.py
FinanceDataReader/fred/data.py
FinanceDataReader/investing/__init__.py
FinanceDataReader/investing/data.py
FinanceDataReader/investing/listing.py
FinanceDataReader/krx/__init__.py
FinanceDataReader/krx/data.py
FinanceDataReader/krx/listing.py
FinanceDataReader/krx/snap.py
FinanceDataReader/nasdaq/__init__.py
FinanceDataReader/nasdaq/listing.py
FinanceDataReader/naver/__init__.py
FinanceDataReader/naver/data.py
FinanceDataReader/naver/listing.py
FinanceDataReader/naver/snap.py
FinanceDataReader/wikipedia/__init__.py
FinanceDataReader/wikipedia/listing.py
FinanceDataReader/yahoo/__init__.py
FinanceDataReader/yahoo/data.py
finance_datareader-0.9.95.dist-info/METADATA
finance_datareader-0.9.95.dist-info/WHEEL
finance_datareader-0.9.95.dist-info/RECORD
