Metadata-Version: 2.4
Name: finance-datareader
Version: 0.9.95
Summary: Financial data reader (price, stock list of markets)
Project-URL: Repository, https://github.com/financedata/financedatareader
Author-email: "FinanceData.KR" <plusjune@financedata.kr>
Maintainer-email: "FinanceData.KR" <plusjune@financedata.kr>
License: MIT License
Keywords: data,finance
Classifier: Development Status :: 5 - Production/Stable
Classifier: License :: OSI Approved :: MIT License
Classifier: Operating System :: OS Independent
Classifier: Programming Language :: Cython
Classifier: Programming Language :: Python
Classifier: Programming Language :: Python :: 3
Classifier: Programming Language :: Python :: 3.9
Classifier: Programming Language :: Python :: 3.10
Classifier: Programming Language :: Python :: 3.11
Classifier: Programming Language :: Python :: 3.12
Requires-Python: >=3.9
Requires-Dist: beautifulsoup4
Requires-Dist: lxml
Requires-Dist: pandas>=1.1.0
Requires-Dist: plotly
Requires-Dist: requests-file
Requires-Dist: requests>=2.3.0
Requires-Dist: tqdm
Provides-Extra: docs
Requires-Dist: sphinx; extra == 'docs'
Provides-Extra: notebook
Requires-Dist: ipykernel; extra == 'notebook'
Requires-Dist: nbformat>=4.2.0; extra == 'notebook'
Provides-Extra: test
Requires-Dist: pytest; extra == 'test'
